transformer_flows/__init__.py
transformer_flows/attention.py
transformer_flows/transformer_flow.py
transformer_flows-0.0.13.dist-info/METADATA
transformer_flows-0.0.13.dist-info/WHEEL
transformer_flows-0.0.13.dist-info/licenses/LICENSE
transformer_flows-0.0.13.dist-info/RECORD
