Metadata-Version: 2.4
Name: transformer-flows
Version: 0.0.13
Summary: Implementation of Transformer Flows (Apple ML) in JAX and Equinox.
Author-email: homerjed <jedhmr@gmail.com>
License-File: LICENSE
Requires-Python: >=3.11
Requires-Dist: beartype>=0.21.0
Requires-Dist: einops>=0.8.1
Requires-Dist: equinox>=0.12.2
Requires-Dist: jax>=0.6.2
Requires-Dist: jaxtyping>=0.3.2
Requires-Dist: matplotlib>=3.10.3
Requires-Dist: ml-collections>=1.1.0
Requires-Dist: optax>=0.2.5
Requires-Dist: tqdm>=4.67.1
Provides-Extra: examples
Requires-Dist: datasets>=3.6.0; extra == 'examples'
